pigs-0.1.0.dist-info/METADATA
pigs-0.1.0.dist-info/WHEEL
pigs/__init__.py
pigs/pigs.cp310-win_amd64.pyd
pigs-0.1.0.dist-info/RECORD
